SwiftyBeaver-0.1.dist-info/DESCRIPTION.rst
SwiftyBeaver-0.1.dist-info/METADATA
SwiftyBeaver-0.1.dist-info/RECORD
SwiftyBeaver-0.1.dist-info/WHEEL
SwiftyBeaver-0.1.dist-info/metadata.json
SwiftyBeaver-0.1.dist-info/top_level.txt
SwiftyBeaver-0.1.dist-info/zip-safe
swiftybeaver/__init__.py
swiftybeaver/tests.py
