Metadata-Version: 2.0
Name: SwiftyBeaver
Version: 0.1
Summary: A Python implementation of the SwiftyBeaver Platform.
Home-page: https://github.com/SwiftyBeaver/SwiftyBeaver-Python
Author: Steffen Ryll
Author-email: steffen.ryll@gmx.de
License: MIT
Platform: UNKNOWN
Classifier: Development Status :: 3 - Alpha
Classifier: License :: OSI Approved :: MIT License
Classifier: Programming Language :: Python
Classifier: Topic :: System :: Logging
Requires-Dist: pycrypto
Requires-Dist: requests
Requires-Dist: requests-futures
